<annotation>
	<folder>bird_new_train</folder>
	<filename>Cardinal_093.jpg</filename>
	<path>C:\Users\Jamie\Desktop\Archive\bird_new_train\Cardinal_093.jpg</path>
	<source>
		<database>Unknown</database>
	</source>
	<size>
		<width>400</width>
		<height>382</height>
		<depth>3</depth>
	</size>
	<segmented>0</segmented>
	<object>
		<name>bird</name>
		<pose>Unspecified</pose>
		<truncated>0</truncated>
		<difficult>0</difficult>
		<bndbox>
			<xmin>54</xmin>
			<ymin>14</ymin>
			<xmax>341</xmax>
			<ymax>326</ymax>
		</bndbox>
	</object>
</annotation>
